LICENSE
MANIFEST.in
README
setup.py
novaclient_auth_secretkey.egg-info/PKG-INFO
novaclient_auth_secretkey.egg-info/SOURCES.txt
novaclient_auth_secretkey.egg-info/dependency_links.txt
novaclient_auth_secretkey.egg-info/entry_points.txt
novaclient_auth_secretkey.egg-info/requires.txt
novaclient_auth_secretkey.egg-info/top_level.txt
novaclient_secretkey/__init__.py
novaclient_secretkey/auth_plugin.py