Metadata-Version: 1.0
Name: novaclient-auth-secretkey
Version: 0.1
Summary: Authentication plugin for novaclient enabling API key and secret key
Home-page: https://github.com/fr33jc/novaclient-auth-secretkey
Author: fr33jc
Author-email: fr33jc@gmail.com
License: MIT
Platform: POSIX
